SuperTerminal/__init__.py
SuperTerminal/api_call.py
SuperTerminal/const_var.py
SuperTerminal/error_handler.py
SuperTerminal/failed_command.py
SuperTerminal/main.py
SuperTerminal/system_run.py
SuperTerminal-1.0.0.dist-info/METADATA
SuperTerminal-1.0.0.dist-info/WHEEL
SuperTerminal-1.0.0.dist-info/entry_points.txt
SuperTerminal-1.0.0.dist-info/top_level.txt
SuperTerminal-1.0.0.dist-info/RECORD
