Metadata-Version: 2.1
Name: SuperTerminal
Version: 1.0.0
Summary: Natural Language to Terminal Command Translator.
Home-page: https://github.com/Kiarash-Karami/SuperTerminal
Author: Kiarash Karami
Author-email: Kiarash_Karami@outlook.com
Requires-Python: >=3.6
Requires-Dist: groq
